[{
	"ID": "1",
	"Title": "The Scriptures are Inspired by God",
	"Header": "The Scriptures, both the Old and New Testaments, are verbally inspired of God and are the revelation of God to man, the infallible, authoritative rule of faith and conduct.",
	"Scripture1": "2 Timothy 3:15-17"
},
{
	"ID": "2",
	"Title": "There is only One True God",
	"Header": "The one true God has revealed Himself as the eternally self-existent 'I AM,' the Creator of heaven and earth and the Redeemer of mankind. He has further revealed Himself as embodying the principles of relationship and association as Father, Son and Holy Spirit."
}]